random_lib_debug/__init__.py
random_lib_debug/random_lib_debug.py
random_lib_debug-0.3.5.dist-info/METADATA
random_lib_debug-0.3.5.dist-info/WHEEL
random_lib_debug-0.3.5.dist-info/top_level.txt
random_lib_debug-0.3.5.dist-info/RECORD
