Metadata-Version: 2.1
Name: random_lib_debug
Version: 0.3.5
Summary: A description of random_lib_debug.
Author: Your Name
Author-email: Your Name <you@example.com>
